pydevmgr_core/__init__.py
pydevmgr_core/base/__init__.py
pydevmgr_core/base/alias.py
pydevmgr_core/base/base.py
pydevmgr_core/base/dataclass.py
pydevmgr_core/base/datamodel.py
pydevmgr_core/base/decorators.py
pydevmgr_core/base/defaults_var.py
pydevmgr_core/base/device.py
pydevmgr_core/base/download.py
pydevmgr_core/base/engine.py
pydevmgr_core/base/interface.py
pydevmgr_core/base/io.py
pydevmgr_core/base/makers.py
pydevmgr_core/base/manager.py
pydevmgr_core/base/model_var.py
pydevmgr_core/base/monitor.py
pydevmgr_core/base/monitor_back.py
pydevmgr_core/base/node.py
pydevmgr_core/base/node_alias.py
pydevmgr_core/base/object_path.py
pydevmgr_core/base/register.py
pydevmgr_core/base/rpc.py
pydevmgr_core/base/upload.py
pydevmgr_core/base/vtype.py
pydevmgr_core/base/wait.py
pydevmgr_core/data_objects/__init__.py
pydevmgr_core/data_objects/device.py
pydevmgr_core/data_objects/engine.py
pydevmgr_core/data_objects/interface.py
pydevmgr_core/data_objects/manager.py
pydevmgr_core/data_objects/node.py
pydevmgr_core/decorators.py
pydevmgr_core/factories.py
pydevmgr_core/io.py
pydevmgr_core/misc/__init__.py
pydevmgr_core/misc/math_parser.py
pydevmgr_core/nodes.py
pydevmgr_core/np_nodes.py
pydevmgr_core/parsers.py
pydevmgr_core/signals.py
pydevmgr_core-0.6a8.dist-info/WHEEL
pydevmgr_core-0.6a8.dist-info/METADATA
pydevmgr_core-0.6a8.dist-info/RECORD
