Metadata-Version: 2.1
Name: pydevmgr-core
Version: 0.6a8
Summary: Python package to handle distributed device handling
License: Creative Commons Attribution-Noncommercial-Share Alike license
Author: Sylvain Guieu
Author-email: sylvain.guieu@univ-grenoble-alpes.fr
Requires-Python: >=3.7,<4.0
Classifier: License :: Other/Proprietary License
Classifier: Programming Language :: Python :: 3
Classifier: Programming Language :: Python :: 3.7
Classifier: Programming Language :: Python :: 3.8
Classifier: Programming Language :: Python :: 3.9
Classifier: Programming Language :: Python :: 3.10
Classifier: Programming Language :: Python :: 3.11
Requires-Dist: get-annotations (>=0.1.2,<0.2.0)
Requires-Dist: py-expression-eval (>=0.3.14,<0.4.0)
Requires-Dist: pydantic (>=1.9,<2.0)
Requires-Dist: systemy (>=0.2.a3)
Requires-Dist: valueparser (>=0.2.a1)
